DCACP/__init__.py
ODPHAC-0.0.1.dist-info/LICENSE
ODPHAC-0.0.1.dist-info/METADATA
ODPHAC-0.0.1.dist-info/WHEEL
ODPHAC-0.0.1.dist-info/top_level.txt
ODPHAC-0.0.1.dist-info/RECORD
