Metadata-Version: 2.1
Name: ODPHAC
Version: 0.0.1
Summary: An outlier detection strategy for spatial free path-finding based on hierarchical ant colonies
Home-page: https://github.com/YF-W/ODPHAC
Author: yf_123
Author-email: wangyuefei@cdu.edu.cn
License: UNKNOWN
Platform: UNKNOWN
Classifier: Programming Language :: Python :: 3
Classifier: License :: OSI Approved :: MIT License
Classifier: Operating System :: OS Independent
Requires-Python: >=3
License-File: LICENSE
Requires-Dist: matplotlib (>=3.3.2)
Requires-Dist: numpy (==1.19.2)
Requires-Dist: scipy (>=1.5.2)
